ebhealthcheck/__init__.py
ebhealthcheck/apps.py
django_ebhealthcheck-2.0.1.dist-info/LICENSE
django_ebhealthcheck-2.0.1.dist-info/METADATA
django_ebhealthcheck-2.0.1.dist-info/WHEEL
django_ebhealthcheck-2.0.1.dist-info/top_level.txt
django_ebhealthcheck-2.0.1.dist-info/RECORD
