Metadata-Version: 2.1
Name: django-ebhealthcheck
Version: 2.0.1
Summary: Django app to add an instance's public IP to ALLOWED_HOSTS for Elastic Beanstalk's health check system
Home-page: https://github.com/sjkingo/django-ebhealthcheck
Author: Sam Kingston
Author-email: sjkingo88@gmail.com
License: BSD
Platform: UNKNOWN
Classifier: Development Status :: 5 - Production/Stable
Classifier: Framework :: Django
Classifier: Intended Audience :: Developers
Classifier: License :: OSI Approved :: BSD License
Classifier: Operating System :: OS Independent
Classifier: Programming Language :: Python
Classifier: Topic :: Software Development :: Libraries :: Python Modules
Requires-Dist: requests
